MultiTrain/__init__.py
MultiTrain/__version__.py
MultiTrain/classification/__init__.py
MultiTrain/classification/classification_models.py
MultiTrain/errors/__init__.py
MultiTrain/errors/errors.py
MultiTrain/regression/__init__.py
MultiTrain/regression/regression_models.py
MultiTrain/test/__init__.py
MultiTrain/test/classification_test.py
MultiTrain/test/regression_test.py
MultiTrain/test/utils_test.py
MultiTrain/utils/__init__.py
MultiTrain/utils/utils.py
MultiTrain-1.0.1.dist-info/LICENSE
MultiTrain-1.0.1.dist-info/METADATA
MultiTrain-1.0.1.dist-info/WHEEL
MultiTrain-1.0.1.dist-info/top_level.txt
MultiTrain-1.0.1.dist-info/RECORD
