Metadata-Version: 2.2
Name: MultiTrain
Version: 1.0.1
Summary: MultiTrain is a user-friendly tool that lets you train several machine learning models at once on your dataset, helping you easily find the best model for your needs.
Home-page: https://github.com/LOVE-DOCTOR/MultiTrain
Author: Shittu Samson
Author-email: tunexo885@gmail.com
Maintainer: Shittu Samson
Maintainer-email: tunex885@gmail.com
Keywords: multitrain,multi,train,MultiTrain,multiclass,classifier,automl,AutoML,train multiple models
Classifier: Programming Language :: Python :: 3
Classifier: Programming Language :: Python :: 3.6
Classifier: Programming Language :: Python :: 3.7
Classifier: Programming Language :: Python :: 3.8
Classifier: Programming Language :: Python :: 3.9
Classifier: Programming Language :: Python :: 3.10
Classifier: License :: OSI Approved :: MIT License
Classifier: Operating System :: OS Independent
Classifier: Natural Language :: English
Classifier: Development Status :: 5 - Production/Stable
Classifier: Framework :: Jupyter
Classifier: Topic :: Scientific/Engineering :: Artificial Intelligence
Classifier: Intended Audience :: Developers
Classifier: Topic :: Software Development :: Libraries :: Python Modules
Requires-Python: >=3.8
License-File: LICENSE
Requires-Dist: catboost<1.3.0,>=1.2.7
Requires-Dist: lightgbm<4.6.0,>=4.5.0
Requires-Dist: setuptools
Requires-Dist: jupyter==1.1.1
Requires-Dist: ipywidgets==8.0.2
Requires-Dist: matplotlib<3.9.4,>=3.7.1
Requires-Dist: pandas<2.0.3,>=2.0.0
Requires-Dist: plotly<6.1.0,>=6.0.0
Requires-Dist: pytest<8.4.0,>=8.3.4
Requires-Dist: scikit-learn==1.3.2
Requires-Dist: seaborn<0.14.0,>=0.13.2
Requires-Dist: xgboost<2.1.0,>=1.7.0
Requires-Dist: tqdm<4.65.0,>=4.64.0
Requires-Dist: ipython<8.18.1,>=8.10.0
